chime_frb_constants/__init__.py
chime_frb_constants/frange.py
chime_frb_constants-2020.12.dist-info/LICENSE
chime_frb_constants-2020.12.dist-info/WHEEL
chime_frb_constants-2020.12.dist-info/METADATA
chime_frb_constants-2020.12.dist-info/RECORD
