Metadata-Version: 2.1
Name: chime-frb-constants
Version: 2020.12
Summary: CHIME/FRB Constants
Home-page: https://github.com/CHIMEFRB/frb-constants
License: MIT
Author: Shiny Brar
Author-email: charanjotbrar@gmail.com
Requires-Python: >=3.6
Classifier: Development Status :: 4 - Beta
Classifier: Intended Audience :: Developers
Classifier: Intended Audience :: Education
Classifier: Intended Audience :: Science/Research
Classifier: License :: OSI Approved :: MIT License
Classifier: Programming Language :: Python :: 3
Classifier: Programming Language :: Python :: 3.6
Classifier: Programming Language :: Python :: 3.7
Classifier: Programming Language :: Python :: 3.8
Classifier: Programming Language :: Python :: 3.9
Classifier: Topic :: Scientific/Engineering :: Astronomy
Classifier: Topic :: Software Development :: Libraries :: Python Modules
Project-URL: Documentation, https://github.com/CHIMEFRB/frb-constants
Project-URL: Repository, https://github.com/CHIMEFRB/frb-constants
